code_tokenizers/__init__.py
code_tokenizers/_modidx.py
code_tokenizers/cli.py
code_tokenizers/core.py
code_tokenizers/helpers.py
code_tokenizers/grammars/__init__.py
code_tokenizers/grammars/python/__init__.py
code_tokenizers/grammars/python/examples/__init__.py
code_tokenizers/grammars/python/examples/compound-statement-without-trailing-newline.py
code_tokenizers/grammars/python/examples/crlf-line-endings.py
code_tokenizers/grammars/python/examples/mixed-spaces-tabs.py
code_tokenizers/grammars/python/examples/multiple-newlines.py
code_tokenizers/grammars/python/examples/python2-grammar-crlf.py
code_tokenizers/grammars/python/examples/python2-grammar.py
code_tokenizers/grammars/python/examples/python3-grammar-crlf.py
code_tokenizers/grammars/python/examples/python3-grammar.py
code_tokenizers/grammars/python/examples/python3.8_grammar.py
code_tokenizers/grammars/python/examples/simple-statements-without-trailing-newline.py
code_tokenizers/grammars/python/examples/tabs.py
code_tokenizers/grammars/python/examples/trailing-whitespace.py
code_tokenizers/grammars/python/test/__init__.py
code_tokenizers/grammars/python/test/highlight/__init__.py
code_tokenizers/grammars/python/test/highlight/keywords.py
code_tokenizers/grammars/python/test/highlight/parameters.py
code_tokenizers/grammars/python/test/highlight/pattern_matching.py
code_tokenizers/grammars/tree-sitter-python/__init__.py
code_tokenizers/grammars/tree-sitter-python/examples/__init__.py
code_tokenizers/grammars/tree-sitter-python/examples/compound-statement-without-trailing-newline.py
code_tokenizers/grammars/tree-sitter-python/examples/crlf-line-endings.py
code_tokenizers/grammars/tree-sitter-python/examples/mixed-spaces-tabs.py
code_tokenizers/grammars/tree-sitter-python/examples/multiple-newlines.py
code_tokenizers/grammars/tree-sitter-python/examples/python2-grammar-crlf.py
code_tokenizers/grammars/tree-sitter-python/examples/python2-grammar.py
code_tokenizers-0.0.5.dist-info/LICENSE
code_tokenizers-0.0.5.dist-info/METADATA
code_tokenizers-0.0.5.dist-info/WHEEL
code_tokenizers-0.0.5.dist-info/entry_points.txt
code_tokenizers-0.0.5.dist-info/top_level.txt
code_tokenizers-0.0.5.dist-info/RECORD
