Metadata-Version: 2.1
Name: code-tokenizers
Version: 0.0.5
Summary: Aligning BPE and AST
Home-page: https://github.com/ncoop57/code_tokenizers
Author: ncoop57
Author-email: nacooper01@wm.edu
License: Apache Software License 2.0
Keywords: nbdev jupyter notebook python tokenizer bpe ast
Classifier: Development Status :: 4 - Beta
Classifier: Intended Audience :: Developers
Classifier: Natural Language :: English
Classifier: Programming Language :: Python :: 3.7
Classifier: Programming Language :: Python :: 3.8
Classifier: Programming Language :: Python :: 3.9
Classifier: Programming Language :: Python :: 3.10
Classifier: License :: OSI Approved :: Apache Software License
Requires-Python: >=3.7
License-File: LICENSE
Requires-Dist: fastcore
Requires-Dist: pandas
Requires-Dist: transformers (<5)
Requires-Dist: tree-sitter (==0.20.1)
Provides-Extra: dev
Requires-Dist: black[jupyter] ; extra == 'dev'
Requires-Dist: datasets (<3) ; extra == 'dev'
Requires-Dist: nbdev (<3) ; extra == 'dev'
Requires-Dist: twine ; extra == 'dev'
